py_questdb/__init__.py
py_questdb/db.py
py_questdb/db_types.py
py_questdb-0.1.0.dist-info/METADATA
py_questdb-0.1.0.dist-info/WHEEL
py_questdb-0.1.0.dist-info/RECORD
