Metadata-Version: 2.1
Name: py-questdb
Version: 0.1.0
Summary: Python interface for QuestDB
License: MIT
Author: idatsy
Author-email: stefan@ranvier.co.uk
Requires-Python: >=3.12,<4.0
Classifier: License :: OSI Approved :: MIT License
Classifier: Programming Language :: Python :: 3
Classifier: Programming Language :: Python :: 3.12
Requires-Dist: aiohttp (>=3.10.3,<4.0.0)
Requires-Dist: msgspec (>=0.18.6,<0.19.0)
Requires-Dist: pandas (>=2.2.2,<3.0.0)
Requires-Dist: questdb (>=2.0.3,<3.0.0)
Requires-Dist: requests (>=2.32.3,<3.0.0)
